{
  "protocol_version" : "0.0.5",
  "configuration" : {
    "version" : "(6.6.0) ((no/bef1e633581)",
    "tlc" : "normal",
    "sigsgev" : "normal",
    "notifications" : "kqueue",
    "architecture" : "amd64",
    "disabled_features" : "none",
    "smallconfig" : "disabled",
    "bigarrays" : "disabled",
    "softdebug" : "enabled",
    "interpreter" : "enabled",
    "llvm_support" : "disabled",
    "suspend" : "preemptive"
  },
  "memory" : {
    "Resident Size" : "415465472",
    "Virtual Size" : "6765875200",
    "minor_gc_time" : "24042",
    "major_gc_time" : "47603",
    "minor_gc_count" : "7",
    "major_gc_count" : "8",
    "major_gc_time_concurrent" : "0"
 },
  "threads" : [
 {
    "is_managed" : false,
    "offset_free_hash" : "0x0",
    "offset_rich_hash" : "0x0",
    "crashed" : false,
    "native_thread_id" : "0x700004de7000",
    "thread_info_addr" : "0x7fa92a0a4000",
    "thread_name" : "Finalizer",
    "ctx" : {
      "IP" : "0x7fff711f6e36",
      "SP" : "0x700004de6e08",
      "BP" : "0x700004de6ec0"
  },
    "unmanaged_frames" : [
  {
      "is_managed" : "false",
      "native_address" : "0x10fe4c346",
      "native_offset" : "0x00000"
   }
,
  {
      "is_managed" : "false",
      "native_address" : "0x1100074f1",
      "native_offset" : "0x00000"
   }
,
  {
      "is_managed" : "false",
      "native_address" : "0x110007237",
      "native_offset" : "0x00000"
   }
,
  {
      "is_managed" : "false",
      "native_address" : "0x10fe5c57c",
      "native_offset" : "0x00000"
   }
,
  {
      "is_managed" : "false",
      "native_address" : "0x7fff712ae5fd",
      "native_offset" : "0x00000"
   }
,
  {
      "is_managed" : "false",
      "native_address" : "0x7fa930718ef0",
      "native_offset" : "0x00000"
   }
,
  {
      "is_managed" : "false",
      "native_address" : "0x110008026",
      "native_offset" : "0x00000"
   }
,
  {
      "is_managed" : "false",
      "native_address" : "0x110007e87",
      "native_offset" : "0x00000"
   }
,
  {
      "is_managed" : "false",
      "native_address" : "0x7fff712ba109",
      "native_offset" : "0x00000"
   }
,
  {
      "is_managed" : "false",
      "native_address" : "0x7fff712b5b8b",
      "native_offset" : "0x00000"
   }

  ]
 },
 {
    "is_managed" : false,
    "offset_free_hash" : "0x0",
    "offset_rich_hash" : "0x0",
    "crashed" : true,
    "native_thread_id" : "0x121ceedc0",
    "thread_info_addr" : "0x7fa92a879e00",
    "thread_name" : "tid_307",
    "ctx" : {
      "IP" : "0x11285a444",
      "SP" : "0x7ffedfe802c0",
      "BP" : "0x7ffedfe802c0"
  },
    "unmanaged_frames" : [
  {
      "is_managed" : "false",
      "native_address" : "0x10fe4c346",
      "native_offset" : "0x00000"
   }
,
  {
      "is_managed" : "false",
      "native_address" : "0x1100074f1",
      "native_offset" : "0x00000"
   }
,
  {
      "is_managed" : "false",
      "native_address" : "0x110007b8b",
      "native_offset" : "0x00000"
   }
,
  {
      "is_managed" : "false",
      "native_address" : "0x10fe5d52e",
      "native_offset" : "0x00000"
   }
,
  {
      "is_managed" : "false",
      "native_address" : "0x10fe50bf5",
      "native_offset" : "0x00000"
   }
,
  {
      "is_managed" : "false",
      "native_address" : "0x10fe647ef",
      "native_offset" : "0x00000"
   }
,
  {
      "is_managed" : "false",
      "native_address" : "0x7fff712ae5fd",
      "native_offset" : "0x00000"
   }
,
  {
      "is_managed" : "true",
      "guid" : "D8EB7115-9C63-438F-B023-6E1D6B3A8EF1",
      "token" : "0x00000",
      "native_offset" : "0x0",
      "filename" : "GodotSharp.dll",
      "sizeofimage" : "0x248000",
      "timestamp" : "0x0",
      "il_offset" : "0x00000"
   }
,
  {
      "is_managed" : "false",
      "native_address" : "0x1105f00c3",
      "native_offset" : "0x00000"
   }
,
  {
      "is_managed" : "false",
      "native_address" : "0x112805b39",
      "native_offset" : "0x00000"
   }
,
  {
      "is_managed" : "false",
      "native_address" : "0x1127e58c5",
      "native_offset" : "0x00000"
   }
,
  {
      "is_managed" : "false",
      "native_address" : "0x1127d82da",
      "native_offset" : "0x00000"
   }
,
  {
      "is_managed" : "false",
      "native_address" : "0x1127d85c0",
      "native_offset" : "0x00000"
   }
,
  {
      "is_managed" : "false",
      "native_address" : "0x11182095a",
      "native_offset" : "0x00000"
   }
,
  {
      "is_managed" : "false",
      "native_address" : "0x1100eaed1",
      "native_offset" : "0x00000"
   }
,
  {
      "is_managed" : "false",
      "native_address" : "0x1100bc317",
      "native_offset" : "0x00000"
   }
,
  {
      "is_managed" : "false",
      "native_address" : "0x1100c1221",
      "native_offset" : "0x00000"
   }
,
  {
      "is_managed" : "false",
      "native_address" : "0x7fff710b5cc9",
      "native_offset" : "0x00000"
   }
,
  {
      "is_managed" : "false",
      "native_address" : "0x4",
      "native_offset" : "0x00000"
   }

  ]
 },
 {
    "is_managed" : true,
    "offset_free_hash" : "0x6f1f52038",
    "offset_rich_hash" : "0x6f1f52196",
    "crashed" : false,
    "native_thread_id" : "0x7000052b6000",
    "thread_info_addr" : "0x7fa92bfdea00",
    "thread_name" : "Godot Ide Connection Server",
    "ctx" : {
      "IP" : "0x7fff711fd3be",
      "SP" : "0x7000052b5718",
      "BP" : "0x7000052b5770"
  },
    "managed_frames" : [
  {
      "is_managed" : "false",
      "native_address" : "unregistered"
   }
,
  {
      "is_managed" : "true",
      "guid" : "354FB821-F4C7-47C2-A36E-5688D4D843E2",
      "token" : "0x00000",
      "native_offset" : "0x0",
      "filename" : "System.dll",
      "sizeofimage" : "0x286000",
      "timestamp" : "0x0",
      "il_offset" : "0x00000"
   }
,
  {
      "is_managed" : "true",
      "guid" : "354FB821-F4C7-47C2-A36E-5688D4D843E2",
      "token" : "0x6002731",
      "native_offset" : "0x0",
      "filename" : "System.dll",
      "sizeofimage" : "0x286000",
      "timestamp" : "0x0",
      "il_offset" : "0x0000c"
   }
,
  {
      "is_managed" : "true",
      "guid" : "354FB821-F4C7-47C2-A36E-5688D4D843E2",
      "token" : "0x600272a",
      "native_offset" : "0x0",
      "filename" : "System.dll",
      "sizeofimage" : "0x286000",
      "timestamp" : "0x0",
      "il_offset" : "0x00008"
   }
,
  {
      "is_managed" : "true",
      "guid" : "354FB821-F4C7-47C2-A36E-5688D4D843E2",
      "token" : "0x60027ff",
      "native_offset" : "0x0",
      "filename" : "System.dll",
      "sizeofimage" : "0x286000",
      "timestamp" : "0x0",
      "il_offset" : "0x0001e"
   }
,
  {
      "is_managed" : "true",
      "guid" : "E24C3BD1-219D-43E1-A589-4426048086AC",
      "token" : "0x60000fe",
      "native_offset" : "0x0",
      "filename" : "GodotTools.dll",
      "sizeofimage" : "0x1c000",
      "timestamp" : "0x0",
      "il_offset" : "0x0000f"
   }
,
  {
      "is_managed" : "true",
      "guid" : "8A11CB08-9F00-4648-8A9B-0FB26E056B58",
      "token" : "0x6001f0b",
      "native_offset" : "0x0",
      "filename" : "mscorlib.dll",
      "sizeofimage" : "0x472000",
      "timestamp" : "0x0",
      "il_offset" : "0x00014"
   }
,
  {
      "is_managed" : "true",
      "guid" : "8A11CB08-9F00-4648-8A9B-0FB26E056B58",
      "token" : "0x6001eb3",
      "native_offset" : "0x0",
      "filename" : "mscorlib.dll",
      "sizeofimage" : "0x472000",
      "timestamp" : "0x0",
      "il_offset" : "0x00071"
   }
,
  {
      "is_managed" : "true",
      "guid" : "8A11CB08-9F00-4648-8A9B-0FB26E056B58",
      "token" : "0x6001eb1",
      "native_offset" : "0x0",
      "filename" : "mscorlib.dll",
      "sizeofimage" : "0x472000",
      "timestamp" : "0x0",
      "il_offset" : "0x00000"
   }
,
  {
      "is_managed" : "true",
      "guid" : "8A11CB08-9F00-4648-8A9B-0FB26E056B58",
      "token" : "0x6001eb0",
      "native_offset" : "0x0",
      "filename" : "mscorlib.dll",
      "sizeofimage" : "0x472000",
      "timestamp" : "0x0",
      "il_offset" : "0x0002b"
   }
,
  {
      "is_managed" : "true",
      "guid" : "8A11CB08-9F00-4648-8A9B-0FB26E056B58",
      "token" : "0x6001f0d",
      "native_offset" : "0x0",
      "filename" : "mscorlib.dll",
      "sizeofimage" : "0x472000",
      "timestamp" : "0x0",
      "il_offset" : "0x00008"
   }
,
  {
      "is_managed" : "true",
      "guid" : "8A11CB08-9F00-4648-8A9B-0FB26E056B58",
      "token" : "0x00000",
      "native_offset" : "0x0",
      "filename" : "mscorlib.dll",
      "sizeofimage" : "0x472000",
      "timestamp" : "0x0",
      "il_offset" : "0x00065"
   }

  ],
  "unmanaged_frames" : [
 {
    "is_managed" : "false",
    "native_address" : "0x10fe4c346",
    "native_offset" : "0x00000"
  }
,
 {
    "is_managed" : "false",
    "native_address" : "0x1100074f1",
    "native_offset" : "0x00000"
  }
,
 {
    "is_managed" : "false",
    "native_address" : "0x110007237",
    "native_offset" : "0x00000"
  }
,
 {
    "is_managed" : "false",
    "native_address" : "0x10fe5c57c",
    "native_offset" : "0x00000"
  }
,
 {
    "is_managed" : "false",
    "native_address" : "0x7fff712ae5fd",
    "native_offset" : "0x00000"
  }
,
 {
    "is_managed" : "false",
    "native_address" : "unregistered"
  }
,
 {
    "is_managed" : "false",
    "native_address" : "0x110033912",
    "native_offset" : "0x00000"
  }
,
 {
    "is_managed" : "false",
    "native_address" : "0x10ff4c77c",
    "native_offset" : "0x00000"
  }
,
 {
    "is_managed" : "true",
    "guid" : "354FB821-F4C7-47C2-A36E-5688D4D843E2",
    "token" : "0x00000",
    "native_offset" : "0x0",
    "filename" : "System.dll",
    "sizeofimage" : "0x286000",
    "timestamp" : "0x0",
    "il_offset" : "0x00000"
  }
,
 {
    "is_managed" : "true",
    "guid" : "354FB821-F4C7-47C2-A36E-5688D4D843E2",
    "token" : "0x600272a",
    "native_offset" : "0x0",
    "filename" : "System.dll",
    "sizeofimage" : "0x286000",
    "timestamp" : "0x0",
    "il_offset" : "0x00000"
  }
,
 {
    "is_managed" : "true",
    "guid" : "8A11CB08-9F00-4648-8A9B-0FB26E056B58",
    "token" : "0x6001f0b",
    "native_offset" : "0x0",
    "filename" : "mscorlib.dll",
    "sizeofimage" : "0x472000",
    "timestamp" : "0x0",
    "il_offset" : "0x00000"
  }
,
 {
    "is_managed" : "true",
    "guid" : "8A11CB08-9F00-4648-8A9B-0FB26E056B58",
    "token" : "0x6001eb1",
    "native_offset" : "0x0",
    "filename" : "mscorlib.dll",
    "sizeofimage" : "0x472000",
    "timestamp" : "0x0",
    "il_offset" : "0x00000"
  }
,
 {
    "is_managed" : "false",
    "native_address" : "0x10fe67b57",
    "native_offset" : "0x00000"
  }
,
 {
    "is_managed" : "false",
    "native_address" : "0x10ffadf97",
    "native_offset" : "0x00000"
  }
,
 {
    "is_managed" : "false",
    "native_address" : "0x10ffb4a96",
    "native_offset" : "0x00000"
  }
,
 {
    "is_managed" : "false",
    "native_address" : "0x1100080fa",
    "native_offset" : "0x00000"
  }
,
 {
    "is_managed" : "false",
    "native_address" : "0x110007e87",
    "native_offset" : "0x00000"
  }
,
 {
    "is_managed" : "false",
    "native_address" : "0x7fff712ba109",
    "native_offset" : "0x00000"
  }
,
 {
    "is_managed" : "false",
    "native_address" : "0x7fff712b5b8b",
    "native_offset" : "0x00000"
  }

 ]
},
{
  "is_managed" : false,
  "offset_free_hash" : "0x0",
  "offset_rich_hash" : "0x0",
  "crashed" : false,
  "native_thread_id" : "0x700005b0e000",
  "thread_info_addr" : "0x7fa92ac76a00",
  "thread_name" : "Thread Pool Worker",
  "ctx" : {
    "IP" : "0x7fff711f6e4e",
    "SP" : "0x700005b0de08",
    "BP" : "0x700005b0dec0"
 },
  "unmanaged_frames" : [
 {
    "is_managed" : "false",
    "native_address" : "0x10fe4c346",
    "native_offset" : "0x00000"
  }
,
 {
    "is_managed" : "false",
    "native_address" : "0x1100074f1",
    "native_offset" : "0x00000"
  }
,
 {
    "is_managed" : "false",
    "native_address" : "0x110007237",
    "native_offset" : "0x00000"
  }
,
 {
    "is_managed" : "false",
    "native_address" : "0x10fe5c57c",
    "native_offset" : "0x00000"
  }
,
 {
    "is_managed" : "false",
    "native_address" : "0x7fff712ae5fd",
    "native_offset" : "0x00000"
  }
,
 {
    "is_managed" : "false",
    "native_address" : "0x19972bf40",
    "native_offset" : "0x00000"
  }
,
 {
    "is_managed" : "false",
    "native_address" : "0x110008026",
    "native_offset" : "0x00000"
  }
,
 {
    "is_managed" : "false",
    "native_address" : "0x110007e87",
    "native_offset" : "0x00000"
  }
,
 {
    "is_managed" : "false",
    "native_address" : "0x7fff712ba109",
    "native_offset" : "0x00000"
  }
,
 {
    "is_managed" : "false",
    "native_address" : "0x7fff712b5b8b",
    "native_offset" : "0x00000"
  }

 ]
},
{
  "is_managed" : false,
  "offset_free_hash" : "0x0",
  "offset_rich_hash" : "0x0",
  "crashed" : false,
  "native_thread_id" : "0x70000590b000",
  "thread_info_addr" : "0x7fa92c00f000",
  "thread_name" : "tid_7457",
  "ctx" : {
    "IP" : "0x7fff711f9882",
    "SP" : "0x70000590ad28",
    "BP" : "0x70000590adc0"
 },
  "unmanaged_frames" : [
 {
    "is_managed" : "false",
    "native_address" : "0x10fe4c346",
    "native_offset" : "0x00000"
  }
,
 {
    "is_managed" : "false",
    "native_address" : "0x1100074f1",
    "native_offset" : "0x00000"
  }
,
 {
    "is_managed" : "false",
    "native_address" : "0x110007237",
    "native_offset" : "0x00000"
  }
,
 {
    "is_managed" : "false",
    "native_address" : "0x10fe5c57c",
    "native_offset" : "0x00000"
  }
,
 {
    "is_managed" : "false",
    "native_address" : "0x7fff712ae5fd",
    "native_offset" : "0x00000"
  }
,
 {
    "is_managed" : "false",
    "native_address" : "unregistered"
  }
,
 {
    "is_managed" : "false",
    "native_address" : "0x11008d6f1",
    "native_offset" : "0x00000"
  }
,
 {
    "is_managed" : "false",
    "native_address" : "0x110099a78",
    "native_offset" : "0x00000"
  }
,
 {
    "is_managed" : "false",
    "native_address" : "0x10fffb653",
    "native_offset" : "0x00000"
  }
,
 {
    "is_managed" : "false",
    "native_address" : "0x110008026",
    "native_offset" : "0x00000"
  }
,
 {
    "is_managed" : "false",
    "native_address" : "0x110007e87",
    "native_offset" : "0x00000"
  }
,
 {
    "is_managed" : "false",
    "native_address" : "0x7fff712ba109",
    "native_offset" : "0x00000"
  }
,
 {
    "is_managed" : "false",
    "native_address" : "0x7fff712b5b8b",
    "native_offset" : "0x00000"
  }

 ]
},
{
  "is_managed" : true,
  "offset_free_hash" : "0x6f1f52038",
  "offset_rich_hash" : "0x6f1f52196",
  "crashed" : false,
  "native_thread_id" : "0x7000050b3000",
  "thread_info_addr" : "0x7fa9320c1e00",
  "thread_name" : "Godot Ide Connection Server",
  "ctx" : {
    "IP" : "0x7fff711fd3be",
    "SP" : "0x7000050b2718",
    "BP" : "0x7000050b2770"
 },
  "managed_frames" : [
 {
    "is_managed" : "false",
    "native_address" : "unregistered"
  }
,
 {
    "is_managed" : "true",
    "guid" : "354FB821-F4C7-47C2-A36E-5688D4D843E2",
    "token" : "0x00000",
    "native_offset" : "0x0",
    "filename" : "System.dll",
    "sizeofimage" : "0x286000",
    "timestamp" : "0x0",
    "il_offset" : "0x00000"
  }
,
 {
    "is_managed" : "true",
    "guid" : "354FB821-F4C7-47C2-A36E-5688D4D843E2",
    "token" : "0x6002731",
    "native_offset" : "0x0",
    "filename" : "System.dll",
    "sizeofimage" : "0x286000",
    "timestamp" : "0x0",
    "il_offset" : "0x0000c"
  }
,
 {
    "is_managed" : "true",
    "guid" : "354FB821-F4C7-47C2-A36E-5688D4D843E2",
    "token" : "0x600272a",
    "native_offset" : "0x0",
    "filename" : "System.dll",
    "sizeofimage" : "0x286000",
    "timestamp" : "0x0",
    "il_offset" : "0x00008"
  }
,
 {
    "is_managed" : "true",
    "guid" : "354FB821-F4C7-47C2-A36E-5688D4D843E2",
    "token" : "0x60027ff",
    "native_offset" : "0x0",
    "filename" : "System.dll",
    "sizeofimage" : "0x286000",
    "timestamp" : "0x0",
    "il_offset" : "0x0001e"
  }
,
 {
    "is_managed" : "true",
    "guid" : "E24C3BD1-219D-43E1-A589-4426048086AC",
    "token" : "0x60000fe",
    "native_offset" : "0x0",
    "filename" : "GodotTools.dll",
    "sizeofimage" : "0x1c000",
    "timestamp" : "0x0",
    "il_offset" : "0x0000f"
  }
,
 {
    "is_managed" : "true",
    "guid" : "8A11CB08-9F00-4648-8A9B-0FB26E056B58",
    "token" : "0x6001f0b",
    "native_offset" : "0x0",
    "filename" : "mscorlib.dll",
    "sizeofimage" : "0x472000",
    "timestamp" : "0x0",
    "il_offset" : "0x00014"
  }
,
 {
    "is_managed" : "true",
    "guid" : "8A11CB08-9F00-4648-8A9B-0FB26E056B58",
    "token" : "0x6001eb3",
    "native_offset" : "0x0",
    "filename" : "mscorlib.dll",
    "sizeofimage" : "0x472000",
    "timestamp" : "0x0",
    "il_offset" : "0x00071"
  }
,
 {
    "is_managed" : "true",
    "guid" : "8A11CB08-9F00-4648-8A9B-0FB26E056B58",
    "token" : "0x6001eb1",
    "native_offset" : "0x0",
    "filename" : "mscorlib.dll",
    "sizeofimage" : "0x472000",
    "timestamp" : "0x0",
    "il_offset" : "0x00000"
  }
,
 {
    "is_managed" : "true",
    "guid" : "8A11CB08-9F00-4648-8A9B-0FB26E056B58",
    "token" : "0x6001eb0",
    "native_offset" : "0x0",
    "filename" : "mscorlib.dll",
    "sizeofimage" : "0x472000",
    "timestamp" : "0x0",
    "il_offset" : "0x0002b"
  }
,
 {
    "is_managed" : "true",
    "guid" : "8A11CB08-9F00-4648-8A9B-0FB26E056B58",
    "token" : "0x6001f0d",
    "native_offset" : "0x0",
    "filename" : "mscorlib.dll",
    "sizeofimage" : "0x472000",
    "timestamp" : "0x0",
    "il_offset" : "0x00008"
  }
,
 {
    "is_managed" : "true",
    "guid" : "8A11CB08-9F00-4648-8A9B-0FB26E056B58",
    "token" : "0x00000",
    "native_offset" : "0x0",
    "filename" : "mscorlib.dll",
    "sizeofimage" : "0x472000",
    "timestamp" : "0x0",
    "il_offset" : "0x00065"
  }

 ],
"unmanaged_frames" : [
{
  "is_managed" : "false",
  "native_address" : "0x10fe4c346",
  "native_offset" : "0x00000"
 }
,
{
  "is_managed" : "false",
  "native_address" : "0x1100074f1",
  "native_offset" : "0x00000"
 }
,
{
  "is_managed" : "false",
  "native_address" : "0x110007237",
  "native_offset" : "0x00000"
 }
,
{
  "is_managed" : "false",
  "native_address" : "0x10fe5c57c",
  "native_offset" : "0x00000"
 }
,
{
  "is_managed" : "false",
  "native_address" : "0x7fff712ae5fd",
  "native_offset" : "0x00000"
 }
,
{
  "is_managed" : "false",
  "native_address" : "0x1",
  "native_offset" : "0x00000"
 }
,
{
  "is_managed" : "false",
  "native_address" : "0x110033912",
  "native_offset" : "0x00000"
 }
,
{
  "is_managed" : "false",
  "native_address" : "0x10ff4c77c",
  "native_offset" : "0x00000"
 }
,
{
  "is_managed" : "true",
  "guid" : "354FB821-F4C7-47C2-A36E-5688D4D843E2",
  "token" : "0x00000",
  "native_offset" : "0x0",
  "filename" : "System.dll",
  "sizeofimage" : "0x286000",
  "timestamp" : "0x0",
  "il_offset" : "0x00000"
 }
,
{
  "is_managed" : "true",
  "guid" : "354FB821-F4C7-47C2-A36E-5688D4D843E2",
  "token" : "0x600272a",
  "native_offset" : "0x0",
  "filename" : "System.dll",
  "sizeofimage" : "0x286000",
  "timestamp" : "0x0",
  "il_offset" : "0x00000"
 }
,
{
  "is_managed" : "true",
  "guid" : "8A11CB08-9F00-4648-8A9B-0FB26E056B58",
  "token" : "0x6001f0b",
  "native_offset" : "0x0",
  "filename" : "mscorlib.dll",
  "sizeofimage" : "0x472000",
  "timestamp" : "0x0",
  "il_offset" : "0x00000"
 }
,
{
  "is_managed" : "true",
  "guid" : "8A11CB08-9F00-4648-8A9B-0FB26E056B58",
  "token" : "0x6001eb1",
  "native_offset" : "0x0",
  "filename" : "mscorlib.dll",
  "sizeofimage" : "0x472000",
  "timestamp" : "0x0",
  "il_offset" : "0x00000"
 }
,
{
  "is_managed" : "false",
  "native_address" : "0x10fe67b57",
  "native_offset" : "0x00000"
 }
,
{
  "is_managed" : "false",
  "native_address" : "0x10ffadf97",
  "native_offset" : "0x00000"
 }
,
{
  "is_managed" : "false",
  "native_address" : "0x10ffb4a96",
  "native_offset" : "0x00000"
 }
,
{
  "is_managed" : "false",
  "native_address" : "0x1100080fa",
  "native_offset" : "0x00000"
 }
,
{
  "is_managed" : "false",
  "native_address" : "0x110007e87",
  "native_offset" : "0x00000"
 }
,
{
  "is_managed" : "false",
  "native_address" : "0x7fff712ba109",
  "native_offset" : "0x00000"
 }
,
{
  "is_managed" : "false",
  "native_address" : "0x7fff712b5b8b",
  "native_offset" : "0x00000"
 }

]
},
{
"is_managed" : true,
"offset_free_hash" : "0x912393510",
"offset_rich_hash" : "0x9123936da",
"crashed" : false,
"native_thread_id" : "0x700005708000",
"thread_info_addr" : "0x7fa92a0c7200",
"thread_name" : "Timer-Scheduler",
"ctx" : {
  "IP" : "0x7fff711f9882",
  "SP" : "0x700005707068",
  "BP" : "0x700005707100"
},
"managed_frames" : [
{
  "is_managed" : "false",
  "native_address" : "unregistered"
 }
,
{
  "is_managed" : "true",
  "guid" : "8A11CB08-9F00-4648-8A9B-0FB26E056B58",
  "token" : "0x00000",
  "native_offset" : "0x0",
  "filename" : "mscorlib.dll",
  "sizeofimage" : "0x472000",
  "timestamp" : "0x0",
  "il_offset" : "0x00000"
 }
,
{
  "is_managed" : "true",
  "guid" : "8A11CB08-9F00-4648-8A9B-0FB26E056B58",
  "token" : "0x600203f",
  "native_offset" : "0x0",
  "filename" : "mscorlib.dll",
  "sizeofimage" : "0x472000",
  "timestamp" : "0x0",
  "il_offset" : "0x00044"
 }
,
{
  "is_managed" : "true",
  "guid" : "8A11CB08-9F00-4648-8A9B-0FB26E056B58",
  "token" : "0x600202b",
  "native_offset" : "0x0",
  "filename" : "mscorlib.dll",
  "sizeofimage" : "0x472000",
  "timestamp" : "0x0",
  "il_offset" : "0x00014"
 }
,
{
  "is_managed" : "true",
  "guid" : "8A11CB08-9F00-4648-8A9B-0FB26E056B58",
  "token" : "0x600202a",
  "native_offset" : "0x0",
  "filename" : "mscorlib.dll",
  "sizeofimage" : "0x472000",
  "timestamp" : "0x0",
  "il_offset" : "0x00000"
 }
,
{
  "is_managed" : "true",
  "guid" : "8A11CB08-9F00-4648-8A9B-0FB26E056B58",
  "token" : "0x6002025",
  "native_offset" : "0x0",
  "filename" : "mscorlib.dll",
  "sizeofimage" : "0x472000",
  "timestamp" : "0x0",
  "il_offset" : "0x00019"
 }
,
{
  "is_managed" : "true",
  "guid" : "8A11CB08-9F00-4648-8A9B-0FB26E056B58",
  "token" : "0x6002028",
  "native_offset" : "0x0",
  "filename" : "mscorlib.dll",
  "sizeofimage" : "0x472000",
  "timestamp" : "0x0",
  "il_offset" : "0x00000"
 }
,
{
  "is_managed" : "true",
  "guid" : "8A11CB08-9F00-4648-8A9B-0FB26E056B58",
  "token" : "0x60020e2",
  "native_offset" : "0x0",
  "filename" : "mscorlib.dll",
  "sizeofimage" : "0x472000",
  "timestamp" : "0x0",
  "il_offset" : "0x0003c"
 }
,
{
  "is_managed" : "true",
  "guid" : "8A11CB08-9F00-4648-8A9B-0FB26E056B58",
  "token" : "0x6001f0b",
  "native_offset" : "0x0",
  "filename" : "mscorlib.dll",
  "sizeofimage" : "0x472000",
  "timestamp" : "0x0",
  "il_offset" : "0x00014"
 }
,
{
  "is_managed" : "true",
  "guid" : "8A11CB08-9F00-4648-8A9B-0FB26E056B58",
  "token" : "0x6001eb3",
  "native_offset" : "0x0",
  "filename" : "mscorlib.dll",
  "sizeofimage" : "0x472000",
  "timestamp" : "0x0",
  "il_offset" : "0x00071"
 }
,
{
  "is_managed" : "true",
  "guid" : "8A11CB08-9F00-4648-8A9B-0FB26E056B58",
  "token" : "0x6001eb1",
  "native_offset" : "0x0",
  "filename" : "mscorlib.dll",
  "sizeofimage" : "0x472000",
  "timestamp" : "0x0",
  "il_offset" : "0x00000"
 }
,
{
  "is_managed" : "true",
  "guid" : "8A11CB08-9F00-4648-8A9B-0FB26E056B58",
  "token" : "0x6001eb0",
  "native_offset" : "0x0",
  "filename" : "mscorlib.dll",
  "sizeofimage" : "0x472000",
  "timestamp" : "0x0",
  "il_offset" : "0x0002b"
 }
,
{
  "is_managed" : "true",
  "guid" : "8A11CB08-9F00-4648-8A9B-0FB26E056B58",
  "token" : "0x6001f0d",
  "native_offset" : "0x0",
  "filename" : "mscorlib.dll",
  "sizeofimage" : "0x472000",
  "timestamp" : "0x0",
  "il_offset" : "0x00008"
 }
,
{
  "is_managed" : "true",
  "guid" : "8A11CB08-9F00-4648-8A9B-0FB26E056B58",
  "token" : "0x00000",
  "native_offset" : "0x0",
  "filename" : "mscorlib.dll",
  "sizeofimage" : "0x472000",
  "timestamp" : "0x0",
  "il_offset" : "0x00065"
 }

],
"unmanaged_frames" : [
{
"is_managed" : "false",
"native_address" : "0x10fe4c346",
"native_offset" : "0x00000"
}
,
{
"is_managed" : "false",
"native_address" : "0x1100074f1",
"native_offset" : "0x00000"
}
,
{
"is_managed" : "false",
"native_address" : "0x110007237",
"native_offset" : "0x00000"
}
,
{
"is_managed" : "false",
"native_address" : "0x10fe5c57c",
"native_offset" : "0x00000"
}
,
{
"is_managed" : "false",
"native_address" : "0x7fff712ae5fd",
"native_offset" : "0x00000"
}
,
{
"is_managed" : "false",
"native_address" : "0x7fa92ac77000",
"native_offset" : "0x00000"
}
,
{
"is_managed" : "false",
"native_address" : "0x11008d70d",
"native_offset" : "0x00000"
}
,
{
"is_managed" : "false",
"native_address" : "0x1100268d2",
"native_offset" : "0x00000"
}
,
{
"is_managed" : "false",
"native_address" : "0x110026796",
"native_offset" : "0x00000"
}
,
{
"is_managed" : "false",
"native_address" : "0x110026a17",
"native_offset" : "0x00000"
}
,
{
"is_managed" : "false",
"native_address" : "0x110001af6",
"native_offset" : "0x00000"
}
,
{
"is_managed" : "false",
"native_address" : "0x10ff578a2",
"native_offset" : "0x00000"
}
,
{
"is_managed" : "true",
"guid" : "8A11CB08-9F00-4648-8A9B-0FB26E056B58",
"token" : "0x00000",
"native_offset" : "0x0",
"filename" : "mscorlib.dll",
"sizeofimage" : "0x472000",
"timestamp" : "0x0",
"il_offset" : "0x00000"
}
,
{
"is_managed" : "true",
"guid" : "8A11CB08-9F00-4648-8A9B-0FB26E056B58",
"token" : "0x600202b",
"native_offset" : "0x0",
"filename" : "mscorlib.dll",
"sizeofimage" : "0x472000",
"timestamp" : "0x0",
"il_offset" : "0x00000"
}
,
{
"is_managed" : "true",
"guid" : "8A11CB08-9F00-4648-8A9B-0FB26E056B58",
"token" : "0x6001f0b",
"native_offset" : "0x0",
"filename" : "mscorlib.dll",
"sizeofimage" : "0x472000",
"timestamp" : "0x0",
"il_offset" : "0x00000"
}
,
{
"is_managed" : "true",
"guid" : "8A11CB08-9F00-4648-8A9B-0FB26E056B58",
"token" : "0x6001eb1",
"native_offset" : "0x0",
"filename" : "mscorlib.dll",
"sizeofimage" : "0x472000",
"timestamp" : "0x0",
"il_offset" : "0x00000"
}
,
{
"is_managed" : "false",
"native_address" : "0x10fe67b57",
"native_offset" : "0x00000"
}
,
{
"is_managed" : "false",
"native_address" : "0x10ffadf97",
"native_offset" : "0x00000"
}
,
{
"is_managed" : "false",
"native_address" : "0x10ffb4a96",
"native_offset" : "0x00000"
}
,
{
"is_managed" : "false",
"native_address" : "0x1100080fa",
"native_offset" : "0x00000"
}
,
{
"is_managed" : "false",
"native_address" : "0x110007e87",
"native_offset" : "0x00000"
}
,
{
"is_managed" : "false",
"native_address" : "0x7fff712ba109",
"native_offset" : "0x00000"
}
,
{
"is_managed" : "false",
"native_address" : "0x7fff712b5b8b",
"native_offset" : "0x00000"
}

]
},
{
"is_managed" : false,
"offset_free_hash" : "0x0",
"offset_rich_hash" : "0x0",
"crashed" : false,
"native_thread_id" : "0x700006720000",
"thread_info_addr" : "0x7fa92b85e200",
"thread_name" : "Thread Pool Worker",
"ctx" : {
"IP" : "0x7fff711f6e4e",
"SP" : "0x70000671fe08",
"BP" : "0x70000671fec0"
},
"unmanaged_frames" : [
{
"is_managed" : "false",
"native_address" : "0x10fe4c346",
"native_offset" : "0x00000"
}
,
{
"is_managed" : "false",
"native_address" : "0x1100074f1",
"native_offset" : "0x00000"
}
,
{
"is_managed" : "false",
"native_address" : "0x110007237",
"native_offset" : "0x00000"
}
,
{
"is_managed" : "false",
"native_address" : "0x10fe5c57c",
"native_offset" : "0x00000"
}
,
{
"is_managed" : "false",
"native_address" : "0x7fff712ae5fd",
"native_offset" : "0x00000"
}
,
{
"is_managed" : "false",
"native_address" : "0x1208b1230",
"native_offset" : "0x00000"
}
,
{
"is_managed" : "false",
"native_address" : "0x110008026",
"native_offset" : "0x00000"
}
,
{
"is_managed" : "false",
"native_address" : "0x110007e87",
"native_offset" : "0x00000"
}
,
{
"is_managed" : "false",
"native_address" : "0x7fff712ba109",
"native_offset" : "0x00000"
}
,
{
"is_managed" : "false",
"native_address" : "0x7fff712b5b8b",
"native_offset" : "0x00000"
}

]
},
{
"is_managed" : false,
"offset_free_hash" : "0x0",
"offset_rich_hash" : "0x0",
"crashed" : false,
"native_thread_id" : "0x70000651d000",
"thread_info_addr" : "0x7fa92d009400",
"thread_name" : "Thread Pool Worker",
"ctx" : {
"IP" : "0x7fff711f6e4e",
"SP" : "0x70000651ce08",
"BP" : "0x70000651cec0"
},
"unmanaged_frames" : [
{
"is_managed" : "false",
"native_address" : "0x10fe4c346",
"native_offset" : "0x00000"
}
,
{
"is_managed" : "false",
"native_address" : "0x1100074f1",
"native_offset" : "0x00000"
}
,
{
"is_managed" : "false",
"native_address" : "0x110007237",
"native_offset" : "0x00000"
}
,
{
"is_managed" : "false",
"native_address" : "0x10fe5c57c",
"native_offset" : "0x00000"
}
,
{
"is_managed" : "false",
"native_address" : "0x7fff712ae5fd",
"native_offset" : "0x00000"
}
,
{
"is_managed" : "false",
"native_address" : "0x1208ab460",
"native_offset" : "0x00000"
}
,
{
"is_managed" : "false",
"native_address" : "0x110008026",
"native_offset" : "0x00000"
}
,
{
"is_managed" : "false",
"native_address" : "0x110007e87",
"native_offset" : "0x00000"
}
,
{
"is_managed" : "false",
"native_address" : "0x7fff712ba109",
"native_offset" : "0x00000"
}
,
{
"is_managed" : "false",
"native_address" : "0x7fff712b5b8b",
"native_offset" : "0x00000"
}

]
},
{
"is_managed" : false,
"offset_free_hash" : "0x0",
"offset_rich_hash" : "0x0",
"crashed" : false,
"native_thread_id" : "0x70000631a000",
"thread_info_addr" : "0x7fa9358e9e00",
"thread_name" : "Thread Pool Worker",
"ctx" : {
"IP" : "0x7fff711f6e4e",
"SP" : "0x700006319e08",
"BP" : "0x700006319ec0"
},
"unmanaged_frames" : [
{
"is_managed" : "false",
"native_address" : "0x10fe4c346",
"native_offset" : "0x00000"
}
,
{
"is_managed" : "false",
"native_address" : "0x1100074f1",
"native_offset" : "0x00000"
}
,
{
"is_managed" : "false",
"native_address" : "0x110007237",
"native_offset" : "0x00000"
}
,
{
"is_managed" : "false",
"native_address" : "0x10fe5c57c",
"native_offset" : "0x00000"
}
,
{
"is_managed" : "false",
"native_address" : "0x7fff712ae5fd",
"native_offset" : "0x00000"
}
,
{
"is_managed" : "false",
"native_address" : "0x1208b1230",
"native_offset" : "0x00000"
}
,
{
"is_managed" : "false",
"native_address" : "0x110008026",
"native_offset" : "0x00000"
}
,
{
"is_managed" : "false",
"native_address" : "0x110007e87",
"native_offset" : "0x00000"
}
,
{
"is_managed" : "false",
"native_address" : "0x7fff712ba109",
"native_offset" : "0x00000"
}
,
{
"is_managed" : "false",
"native_address" : "0x7fff712b5b8b",
"native_offset" : "0x00000"
}

]
},
{
"is_managed" : false,
"offset_free_hash" : "0x0",
"offset_rich_hash" : "0x0",
"crashed" : false,
"native_thread_id" : "0x700006117000",
"thread_info_addr" : "0x7fa92d82f400",
"thread_name" : "Thread Pool Worker",
"ctx" : {
"IP" : "0x7fff711f6e4e",
"SP" : "0x700006116e08",
"BP" : "0x700006116ec0"
},
"unmanaged_frames" : [
{
"is_managed" : "false",
"native_address" : "0x10fe4c346",
"native_offset" : "0x00000"
}
,
{
"is_managed" : "false",
"native_address" : "0x1100074f1",
"native_offset" : "0x00000"
}
,
{
"is_managed" : "false",
"native_address" : "0x110007237",
"native_offset" : "0x00000"
}
,
{
"is_managed" : "false",
"native_address" : "0x10fe5c57c",
"native_offset" : "0x00000"
}
,
{
"is_managed" : "false",
"native_address" : "0x7fff712ae5fd",
"native_offset" : "0x00000"
}
,
{
"is_managed" : "false",
"native_address" : "0x1208b1230",
"native_offset" : "0x00000"
}
,
{
"is_managed" : "false",
"native_address" : "0x110008026",
"native_offset" : "0x00000"
}
,
{
"is_managed" : "false",
"native_address" : "0x110007e87",
"native_offset" : "0x00000"
}
,
{
"is_managed" : "false",
"native_address" : "0x7fff712ba109",
"native_offset" : "0x00000"
}
,
{
"is_managed" : "false",
"native_address" : "0x7fff712b5b8b",
"native_offset" : "0x00000"
}

]
},
{
"is_managed" : false,
"offset_free_hash" : "0x0",
"offset_rich_hash" : "0x0",
"crashed" : false,
"native_thread_id" : "0x700005f14000",
"thread_info_addr" : "0x7fa93591aa00",
"thread_name" : "Thread Pool Worker",
"ctx" : {
"IP" : "0x7fff711f6e4e",
"SP" : "0x700005f13e08",
"BP" : "0x700005f13ec0"
},
"unmanaged_frames" : [
{
"is_managed" : "false",
"native_address" : "0x10fe4c346",
"native_offset" : "0x00000"
}
,
{
"is_managed" : "false",
"native_address" : "0x1100074f1",
"native_offset" : "0x00000"
}
,
{
"is_managed" : "false",
"native_address" : "0x110007237",
"native_offset" : "0x00000"
}
,
{
"is_managed" : "false",
"native_address" : "0x10fe5c57c",
"native_offset" : "0x00000"
}
,
{
"is_managed" : "false",
"native_address" : "0x7fff712ae5fd",
"native_offset" : "0x00000"
}
,
{
"is_managed" : "false",
"native_address" : "0x1208b1230",
"native_offset" : "0x00000"
}
,
{
"is_managed" : "false",
"native_address" : "0x110008026",
"native_offset" : "0x00000"
}
,
{
"is_managed" : "false",
"native_address" : "0x110007e87",
"native_offset" : "0x00000"
}
,
{
"is_managed" : "false",
"native_address" : "0x7fff712ba109",
"native_offset" : "0x00000"
}
,
{
"is_managed" : "false",
"native_address" : "0x7fff712b5b8b",
"native_offset" : "0x00000"
}

]
},
{
"is_managed" : false,
"offset_free_hash" : "0x0",
"offset_rich_hash" : "0x0",
"crashed" : false,
"native_thread_id" : "0x700005d11000",
"thread_info_addr" : "0x7fa92afb3200",
"thread_name" : "Thread Pool Worker",
"ctx" : {
"IP" : "0x7fff711f6e4e",
"SP" : "0x700005d10e08",
"BP" : "0x700005d10ec0"
},
"unmanaged_frames" : [
{
"is_managed" : "false",
"native_address" : "0x10fe4c346",
"native_offset" : "0x00000"
}
,
{
"is_managed" : "false",
"native_address" : "0x1100074f1",
"native_offset" : "0x00000"
}
,
{
"is_managed" : "false",
"native_address" : "0x110007237",
"native_offset" : "0x00000"
}
,
{
"is_managed" : "false",
"native_address" : "0x10fe5c57c",
"native_offset" : "0x00000"
}
,
{
"is_managed" : "false",
"native_address" : "0x7fff712ae5fd",
"native_offset" : "0x00000"
}
,
{
"is_managed" : "false",
"native_address" : "0x1208b1230",
"native_offset" : "0x00000"
}
,
{
"is_managed" : "false",
"native_address" : "0x110008026",
"native_offset" : "0x00000"
}
,
{
"is_managed" : "false",
"native_address" : "0x110007e87",
"native_offset" : "0x00000"
}
,
{
"is_managed" : "false",
"native_address" : "0x7fff712ba109",
"native_offset" : "0x00000"
}
,
{
"is_managed" : "false",
"native_address" : "0x7fff712b5b8b",
"native_offset" : "0x00000"
}

]
}
]
}